subtraction/__init__.py
sum/__init__.py
calculator_rodrigom-0.0.1.dist-info/METADATA
calculator_rodrigom-0.0.1.dist-info/WHEEL
calculator_rodrigom-0.0.1.dist-info/top_level.txt
calculator_rodrigom-0.0.1.dist-info/RECORD
