Metadata-Version: 2.1
Name: calculator_rodrigom
Version: 0.0.1
Summary: A calculator
Home-page: https://github.com/rodrigomacarini/python_language_fundamentals/tree/main/calculator
Author: Rodrigo M.
Author-email: rodrigofmacarini@gmail.com
Requires-Python: >=3.8
